Metadata-Version: 1.1
Name: obol
Version: 2.0.3
Summary: useradd for ldap
Home-page: https://github.com/hansthen/obol
Author: Hans Then
Author-email: hans.then@gmail.com
License: GPLv3
Download-URL: https://github.com/hansthen/obol/tarball/2.0
Keywords: useradd,groupadd,ldap
Platform: UNKNOWN
Classifier: Development Status :: 4 - Beta
Classifier: Topic :: Utilities
Classifier: License :: OSI Approved :: GNU General Public License v3 (GPLv3)
